docs/conf.py
pyoaev/__init__.py
pyoaev/_version.py
pyoaev/base.py
pyoaev/client.py
pyoaev/exceptions.py
pyoaev/helpers.py
pyoaev/mixins.py
pyoaev/utils.py
pyoaev/apis/__init__.py
pyoaev/apis/attack_pattern.py
pyoaev/apis/collector.py
pyoaev/apis/cve.py
pyoaev/apis/document.py
pyoaev/apis/endpoint.py
pyoaev/apis/inject.py
pyoaev/apis/inject_expectation_trace.py
pyoaev/apis/injector.py
pyoaev/apis/injector_contract.py
pyoaev/apis/kill_chain_phase.py
pyoaev/apis/me.py
pyoaev/apis/organization.py
pyoaev/apis/payload.py
pyoaev/apis/security_platform.py
pyoaev/apis/tag.py
pyoaev/apis/team.py
pyoaev/apis/user.py
pyoaev/apis/inject_expectation/__init__.py
pyoaev/apis/inject_expectation/inject_expectation.py
pyoaev/apis/inject_expectation/model/__init__.py
pyoaev/apis/inject_expectation/model/expectation.py
pyoaev/apis/inputs/__init__.py
pyoaev/apis/inputs/search.py
pyoaev/backends/__init__.py
pyoaev/backends/backend.py
pyoaev/backends/protocol.py
pyoaev/configuration/__init__.py
pyoaev/configuration/configuration.py
pyoaev/configuration/sources.py
pyoaev/contracts/__init__.py
pyoaev/contracts/contract_builder.py
pyoaev/contracts/contract_config.py
pyoaev/contracts/contract_utils.py
pyoaev/contracts/variable_helper.py
pyoaev/daemons/__init__.py
pyoaev/daemons/base_daemon.py
pyoaev/daemons/collector_daemon.py
pyoaev/signatures/__init__.py
pyoaev/signatures/signature_match.py
pyoaev/signatures/signature_type.py
pyoaev/signatures/types.py
pyoaev-2.0.14.dist-info/licenses/LICENSE
scripts/release.py
test/__init__.py
test/apis/__init__.py
test/apis/endpoint/__init__.py
test/apis/endpoint/test_endpoint.py
test/apis/expectation/__init__.py
test/apis/expectation/test_expectation.py
test/apis/injector_contract/__init__.py
test/apis/injector_contract/test_injector_contract.py
test/configuration/__init__.py
test/configuration/test_configuration.py
test/configuration/test_sources.py
test/daemons/__init__.py
test/daemons/test_base_daemon.py
test/daemons/test_collector_daemon.py
test/signatures/__init__.py
pyoaev-2.0.14.dist-info/METADATA
pyoaev-2.0.14.dist-info/WHEEL
pyoaev-2.0.14.dist-info/top_level.txt
pyoaev-2.0.14.dist-info/RECORD
