Metadata-Version: 2.4
Name: pyoaev
Version: 2.0.14
Summary: Python API client for OpenAEV.
Author-email: Filigran <contact@filigran.io>
Maintainer-email: Filigran <contact@filigran.io>
License: Apache-2.0
Classifier: Development Status :: 5 - Production/Stable
Classifier: Intended Audience :: Developers
Classifier: Intended Audience :: Information Technology
Classifier: Intended Audience :: Science/Research
Classifier: License :: OSI Approved :: Apache Software License
Classifier: Natural Language :: English
Classifier: Natural Language :: French
Classifier: Operating System :: OS Independent
Classifier: Programming Language :: Python :: 3
Classifier: Topic :: Security
Classifier: Topic :: Software Development :: Libraries :: Python Modules
Requires-Python: >=3.11
License-File: LICENSE
Requires-Dist: datefinder<0.8,>=0.7.3
Requires-Dist: pika<1.4.0,>=1.3.0
Requires-Dist: python-magic<0.5,>=0.4.27; sys_platform == "linux" or sys_platform == "darwin"
Requires-Dist: python-magic-bin<0.5,>=0.4.14; sys_platform == "win32"
Requires-Dist: python_json_logger<3.4.0,>=3.3.0
Requires-Dist: PyYAML<6.1,>=6.0
Requires-Dist: pydantic<2.12.0,>=2.11.3
Requires-Dist: requests<2.33.0,>=2.32.3
Requires-Dist: setuptools<80.10.0,>=80.9.0
Requires-Dist: cachetools<5.6.0,>=5.5.0
Requires-Dist: prometheus-client<0.23.0,>=0.22.1
Requires-Dist: opentelemetry-api<1.36.0,>=1.35.0
Requires-Dist: opentelemetry-sdk<1.36.0,>=1.35.0
Requires-Dist: requests-toolbelt<1.1.0,>=1.0.0
Requires-Dist: dataclasses-json<0.7.0,>=0.6.4
Requires-Dist: thefuzz<0.23,>=0.22
Provides-Extra: dev
Requires-Dist: black<25.2.0,>=25.1.0; extra == "dev"
Requires-Dist: build<1.3.0,>=1.2.1; extra == "dev"
Requires-Dist: isort<6.1.0,>=6.0.0; extra == "dev"
Requires-Dist: types-pytz<2025.3.0.0,>=2025.2.0.20250326; extra == "dev"
Requires-Dist: pre-commit<4.3.0,>=4.2.0; extra == "dev"
Requires-Dist: types-python-dateutil<2.10.0,>=2.9.0; extra == "dev"
Requires-Dist: wheel<0.46.0,>=0.45.1; extra == "dev"
Provides-Extra: doc
Requires-Dist: autoapi<2.1.0,>=2.0.1; extra == "doc"
Requires-Dist: sphinx-autodoc-typehints<3.3.0,>=3.2.0; extra == "doc"
Requires-Dist: sphinx-rtd-theme<3.1.0,>=3.0.2; extra == "doc"
Dynamic: license-file
